{"name":"GalleryController","functions":[{"name":"__construct","access_modifier":"public","params":[""],"line":16,"content":null},{"name":"index","access_modifier":"public","params":[""],"line":22,"content":null},{"name":"show","access_modifier":"public","params":["$gallery_name"],"line":44,"content":null},{"name":"get","access_modifier":"public","params":["$gallery_name","$options = null","$json = true","$user = null"],"line":60,"content":null},{"name":"upload","access_modifier":"public","params":["Request $request"],"line":151,"content":null},{"name":"delete","access_modifier":"public","params":["Request $request","$json = true","$user = null"],"line":193,"content":null},{"name":"getAttributes","access_modifier":"public","params":[""],"line":207,"content":null},{"name":"getMaxLengthGallery","access_modifier":null,"params":[""],"line":214,"content":null},{"name":"getUsedSpaceFromGallery","access_modifier":null,"params":["$gallery_name = null"],"line":219,"content":null},{"name":"availableGalleries","access_modifier":null,"params":[""],"line":283,"content":null},{"name":"FileSizeConvert","access_modifier":null,"params":["$bytes"],"line":318,"content":null},{"name":"ReadDir","access_modifier":null,"params":["$path","$limit = null","$reverse = true"],"line":353,"content":null},{"name":"deleteAll","access_modifier":null,"params":["$user = null"],"line":370,"content":null}]}